pangeo_forge/README.md
pangeo_forge/__init__.py
pangeo_forge/executors.py
pangeo_forge/patterns.py
pangeo_forge/recipe.py
pangeo_forge/storage.py
pangeo_forge/utils.py
tests/__init__.py
tests/conftest.py
tests/http_auth_server.py
tests/test_fixtures.py
tests/test_locking.py
tests/test_patterns.py
tests/test_recipes.py
tests/test_utils.py
pangeo_forge-0.0.0.dist-info/LICENSE
pangeo_forge-0.0.0.dist-info/METADATA
pangeo_forge-0.0.0.dist-info/WHEEL
pangeo_forge-0.0.0.dist-info/entry_points.txt
pangeo_forge-0.0.0.dist-info/top_level.txt
pangeo_forge-0.0.0.dist-info/RECORD
