Metadata-Version: 2.1
Name: pangeo-forge
Version: 0.0.0
Summary: Pipeline tools for building and publishing analysis ready datasets
Home-page: https://github.com/pangeo-forge/pangeo-forge
Maintainer: Joe Hamman
Maintainer-email: jhamman@ucar.edu
License: Apache
Keywords: pangeo,data
Platform: UNKNOWN
Classifier: Development Status :: 1 - Planning
Classifier: License :: OSI Approved :: Apache Software License
Classifier: Operating System :: OS Independent
Classifier: Intended Audience :: Science/Research
Classifier: Programming Language :: Python
Classifier: Programming Language :: Python :: 3
Classifier: Programming Language :: Python :: 3.7
Classifier: Programming Language :: Python :: 3.8
Classifier: Topic :: Scientific/Engineering
Requires-Python: >=3.7
Requires-Dist: setuptools
Requires-Dist: click
Requires-Dist: dask
Requires-Dist: distributed
Requires-Dist: rechunker
Requires-Dist: xarray (>=0.17.1)
Requires-Dist: zarr (>=2.6.0)
Requires-Dist: fsspec[http]
